WuaiPojieLuntanjinghuaJi2019DiyiBufen/README.md
WuaiPojieLuntanjinghuaJi2019DiyiBufen/__init__.py
WuaiPojieLuntanjinghuaJi2019DiyiBufen/__main__.py
WuaiPojieLuntanjinghuaJi2019DiyiBufen/file.epub
WuaiPojieLuntanjinghuaJi2019DiyiBufen/index.html
WuaiPojieLuntanjinghuaJi2019DiyiBufen/css/__init__.py
WuaiPojieLuntanjinghuaJi2019DiyiBufen/css/annotations.css
WuaiPojieLuntanjinghuaJi2019DiyiBufen/css/main.css
WuaiPojieLuntanjinghuaJi2019DiyiBufen/css/normalize.css
WuaiPojieLuntanjinghuaJi2019DiyiBufen/css/popup.css
WuaiPojieLuntanjinghuaJi2019DiyiBufen/font/__init__.py
WuaiPojieLuntanjinghuaJi2019DiyiBufen/font/fontello.eot
WuaiPojieLuntanjinghuaJi2019DiyiBufen/font/fontello.svg
WuaiPojieLuntanjinghuaJi2019DiyiBufen/font/fontello.ttf
WuaiPojieLuntanjinghuaJi2019DiyiBufen/font/fontello.woff
WuaiPojieLuntanjinghuaJi2019DiyiBufen/img/__init__.py
WuaiPojieLuntanjinghuaJi2019DiyiBufen/img/annotator-glyph-sprite.png
WuaiPojieLuntanjinghuaJi2019DiyiBufen/img/annotator-icon-sprite.png
WuaiPojieLuntanjinghuaJi2019DiyiBufen/img/apple-touch-icon.png
WuaiPojieLuntanjinghuaJi2019DiyiBufen/img/cancelfullscreen.png
WuaiPojieLuntanjinghuaJi2019DiyiBufen/img/close.png
WuaiPojieLuntanjinghuaJi2019DiyiBufen/img/fullscreen.png
WuaiPojieLuntanjinghuaJi2019DiyiBufen/img/loader.gif
WuaiPojieLuntanjinghuaJi2019DiyiBufen/img/menu-icon.png
WuaiPojieLuntanjinghuaJi2019DiyiBufen/img/save.png
WuaiPojieLuntanjinghuaJi2019DiyiBufen/img/saved.png
WuaiPojieLuntanjinghuaJi2019DiyiBufen/img/settings-s.png
WuaiPojieLuntanjinghuaJi2019DiyiBufen/img/settings.png
WuaiPojieLuntanjinghuaJi2019DiyiBufen/img/star.png
WuaiPojieLuntanjinghuaJi2019DiyiBufen/js/__init__.py
WuaiPojieLuntanjinghuaJi2019DiyiBufen/js/epub.js
WuaiPojieLuntanjinghuaJi2019DiyiBufen/js/epub.min.js
WuaiPojieLuntanjinghuaJi2019DiyiBufen/js/epub.min.map
WuaiPojieLuntanjinghuaJi2019DiyiBufen/js/hooks.min.js
WuaiPojieLuntanjinghuaJi2019DiyiBufen/js/hooks.min.map
WuaiPojieLuntanjinghuaJi2019DiyiBufen/js/reader.js
wuai_pojie_luntanjinghua_ji_2019_diyi_bufen-2024.3.5.0.dist-info/METADATA
wuai_pojie_luntanjinghua_ji_2019_diyi_bufen-2024.3.5.0.dist-info/WHEEL
wuai_pojie_luntanjinghua_ji_2019_diyi_bufen-2024.3.5.0.dist-info/entry_points.txt
wuai_pojie_luntanjinghua_ji_2019_diyi_bufen-2024.3.5.0.dist-info/top_level.txt
wuai_pojie_luntanjinghua_ji_2019_diyi_bufen-2024.3.5.0.dist-info/RECORD
